COPYING.txt
MANIFEST.in
Makefile
README.md
README.rst
features.en.yhtml2
format.css
heading.en.yhtml2
hello.en.yhtml2
homepage.en.yhtml2
index.en.yhtml2
programming.en.yhtml2
setup.cfg
setup.py
toolchain.en.yhtml2
yml2c
yml2proc
yslt.en.yhtml2
YML2.egg-info/PKG-INFO
YML2.egg-info/SOURCES.txt
YML2.egg-info/dependency_links.txt
YML2.egg-info/entry_points.txt
YML2.egg-info/not-zip-safe
YML2.egg-info/requires.txt
YML2.egg-info/top_level.txt
samples/Customer.java
samples/address.yml2
samples/addresslistenhtml.ysl2
samples/adresslist.yml2
samples/adressliste.yml2
samples/backend.ysl2
samples/blub.svg
samples/blub.yml2
samples/browse.ysl2
samples/bumens.yml2
samples/clike.yml2
samples/ctest.yml2
samples/customer.java.target
samples/customer.xml
samples/customer.xsl
samples/customer.ysl2
samples/ddl.ysl2
samples/debug_test.ysl2
samples/delta.yml2
samples/demo.xmi
samples/dingens.idl
samples/dingens.sql
samples/dingens.xml
samples/dingens.yml2
samples/dml.ysl2
samples/double.yml2
samples/double.ysl2
samples/empty.xml
samples/empty.ysl2
samples/errortest.ysl2
samples/f.yml2
samples/f.ysl2
samples/function.xml
samples/function.yml2
samples/gen.bas
samples/gen_addr_html.ysl2
samples/gen_addr_sql.ysl2
samples/gen_again_java.ysl2
samples/gen_java.ysl2
samples/hello.xsl
samples/hello.yml2
samples/hello.ysl2
samples/i.yml2
samples/idl.yml2
samples/indention.ysl2
samples/list.yml2
samples/macros_test.yml2
samples/manpage.yml2
samples/model.ymi
samples/namespace.ysl2
samples/opertest.ysl2
samples/rechner.ysl2
samples/simple.ysl2
samples/table.yml2
samples/table2ddl.ysl2
samples/text_test.yml2
samples/textest.xml
samples/types.xml
samples/types.yml2
samples/uml.yml2
samples/uml2idl.yml2
samples/uml2sql.yml2
samples/union.ysl2
samples/vorlesung.xmi
samples/webseite.ysl2
samples/xmi2ddl.uml2
samples/xmi2ddl.ysl2
samples/xmi2idl.uml2
samples/xml2.yml2
samples/ydl2idl.ysl2
vim/syntax/yml2.vim
yml2/__init__.py
yml2/backend.py
yml2/manpage.yml2
yml2/pyPEG.py
yml2/standardlib.ysl2
yml2/xml2yml.ysl2
yml2/yml2.py
yml2/yml2c.py
yml2/yml2proc.py
yml2/yslt.yml2
yml2.egg-info/PKG-INFO
yml2.egg-info/SOURCES.txt
yml2.egg-info/dependency_links.txt
yml2.egg-info/entry_points.txt
yml2.egg-info/not-zip-safe
yml2.egg-info/requires.txt
yml2.egg-info/top_level.txt